<annotation>
	<folder>labels</folder>
	<filename>095.png</filename>
	<path>/dataset/images/raw_images/095.png</path>
	<source>
		<database>Unknown</database>
	</source>
	<size>
		<width>512</width>
		<height>512</height>
		<depth>1</depth>
	</size>
	<segmented>0</segmented>
	<object>
		<name>one</name>
		<pose>Unspecified</pose>
		<truncated>0</truncated>
		<difficult>0</difficult>
		<bndbox>
			<xmin>85</xmin>
			<ymin>171</ymin>
			<xmax>99</xmax>
			<ymax>177</ymax>
		</bndbox>
	</object>
	<object>
		<name>one</name>
		<pose>Unspecified</pose>
		<truncated>0</truncated>
		<difficult>0</difficult>
		<bndbox>
			<xmin>220</xmin>
			<ymin>171</ymin>
			<xmax>234</xmax>
			<ymax>176</ymax>
		</bndbox>
	</object>
	<object>
		<name>many</name>
		<pose>Unspecified</pose>
		<truncated>0</truncated>
		<difficult>0</difficult>
		<bndbox>
			<xmin>41</xmin>
			<ymin>125</ymin>
			<xmax>46</xmax>
			<ymax>140</ymax>
		</bndbox>
	</object>
	<object>
		<name>many</name>
		<pose>Unspecified</pose>
		<truncated>0</truncated>
		<difficult>0</difficult>
		<bndbox>
			<xmin>121</xmin>
			<ymin>70</ymin>
			<xmax>140</xmax>
			<ymax>76</ymax>
		</bndbox>
	</object>
	<object>
		<name>many</name>
		<pose>Unspecified</pose>
		<truncated>0</truncated>
		<difficult>0</difficult>
		<bndbox>
			<xmin>178</xmin>
			<ymin>70</ymin>
			<xmax>193</xmax>
			<ymax>75</ymax>
		</bndbox>
	</object>
	<object>
		<name>many</name>
		<pose>Unspecified</pose>
		<truncated>0</truncated>
		<difficult>0</difficult>
		<bndbox>
			<xmin>253</xmin>
			<ymin>111</ymin>
			<xmax>259</xmax>
			<ymax>135</ymax>
		</bndbox>
	</object>
	<object>
		<name>many</name>
		<pose>Unspecified</pose>
		<truncated>0</truncated>
		<difficult>0</difficult>
		<bndbox>
			<xmin>314</xmin>
			<ymin>70</ymin>
			<xmax>326</xmax>
			<ymax>76</ymax>
		</bndbox>
	</object>
	<object>
		<name>many</name>
		<pose>Unspecified</pose>
		<truncated>0</truncated>
		<difficult>0</difficult>
		<bndbox>
			<xmin>369</xmin>
			<ymin>70</ymin>
			<xmax>382</xmax>
			<ymax>76</ymax>
		</bndbox>
	</object>
	<object>
		<name>entity</name>
		<pose>Unspecified</pose>
		<truncated>0</truncated>
		<difficult>0</difficult>
		<bndbox>
			<xmin>1</xmin>
			<ymin>53</ymin>
			<xmax>121</xmax>
			<ymax>127</ymax>
		</bndbox>
	</object>
	<object>
		<name>entity</name>
		<pose>Unspecified</pose>
		<truncated>1</truncated>
		<difficult>0</difficult>
		<bndbox>
			<xmin>99</xmin>
			<ymin>159</ymin>
			<xmax>221</xmax>
			<ymax>203</ymax>
		</bndbox>
	</object>
	<object>
		<name>entity</name>
		<pose>Unspecified</pose>
		<truncated>0</truncated>
		<difficult>0</difficult>
		<bndbox>
			<xmin>193</xmin>
			<ymin>54</ymin>
			<xmax>314</xmax>
			<ymax>112</ymax>
		</bndbox>
	</object>
	<object>
		<name>entity</name>
		<pose>Unspecified</pose>
		<truncated>0</truncated>
		<difficult>0</difficult>
		<bndbox>
			<xmin>319</xmin>
			<ymin>1</ymin>
			<xmax>376</xmax>
			<ymax>35</ymax>
		</bndbox>
	</object>
	<object>
		<name>weak_entity</name>
		<pose>Unspecified</pose>
		<truncated>1</truncated>
		<difficult>0</difficult>
		<bndbox>
			<xmin>381</xmin>
			<ymin>48</ymin>
			<xmax>512</xmax>
			<ymax>102</ymax>
		</bndbox>
	</object>
	<object>
		<name>rel</name>
		<pose>Unspecified</pose>
		<truncated>0</truncated>
		<difficult>0</difficult>
		<bndbox>
			<xmin>24</xmin>
			<ymin>141</ymin>
			<xmax>64</xmax>
			<ymax>160</ymax>
		</bndbox>
	</object>
	<object>
		<name>rel</name>
		<pose>Unspecified</pose>
		<truncated>0</truncated>
		<difficult>0</difficult>
		<bndbox>
			<xmin>237</xmin>
			<ymin>136</ymin>
			<xmax>275</xmax>
			<ymax>155</ymax>
		</bndbox>
	</object>
	<object>
		<name>rel</name>
		<pose>Unspecified</pose>
		<truncated>0</truncated>
		<difficult>0</difficult>
		<bndbox>
			<xmin>141</xmin>
			<ymin>64</ymin>
			<xmax>177</xmax>
			<ymax>83</ymax>
		</bndbox>
	</object>
	<object>
		<name>ident_rel</name>
		<pose>Unspecified</pose>
		<truncated>0</truncated>
		<difficult>0</difficult>
		<bndbox>
			<xmin>327</xmin>
			<ymin>61</ymin>
			<xmax>368</xmax>
			<ymax>85</ymax>
		</bndbox>
	</object>
</annotation>