<annotation>
	<folder>labels</folder>
	<filename>115.png</filename>
	<path>/dataset/images/raw_images/115.png</path>
	<source>
		<database>Unknown</database>
	</source>
	<size>
		<width>512</width>
		<height>512</height>
		<depth>1</depth>
	</size>
	<segmented>0</segmented>
	<object>
		<name>one</name>
		<pose>Unspecified</pose>
		<truncated>0</truncated>
		<difficult>0</difficult>
		<bndbox>
			<xmin>150</xmin>
			<ymin>197</ymin>
			<xmax>174</xmax>
			<ymax>204</ymax>
		</bndbox>
	</object>
	<object>
		<name>one</name>
		<pose>Unspecified</pose>
		<truncated>0</truncated>
		<difficult>0</difficult>
		<bndbox>
			<xmin>348</xmin>
			<ymin>164</ymin>
			<xmax>372</xmax>
			<ymax>173</ymax>
		</bndbox>
	</object>
	<object>
		<name>many</name>
		<pose>Unspecified</pose>
		<truncated>0</truncated>
		<difficult>0</difficult>
		<bndbox>
			<xmin>151</xmin>
			<ymin>77</ymin>
			<xmax>172</xmax>
			<ymax>88</ymax>
		</bndbox>
	</object>
	<object>
		<name>many</name>
		<pose>Unspecified</pose>
		<truncated>0</truncated>
		<difficult>0</difficult>
		<bndbox>
			<xmin>347</xmin>
			<ymin>288</ymin>
			<xmax>372</xmax>
			<ymax>297</ymax>
		</bndbox>
	</object>
	<object>
		<name>entity</name>
		<pose>Unspecified</pose>
		<truncated>0</truncated>
		<difficult>0</difficult>
		<bndbox>
			<xmin>9</xmin>
			<ymin>162</ymin>
			<xmax>150</xmax>
			<ymax>239</ymax>
		</bndbox>
	</object>
	<object>
		<name>entity</name>
		<pose>Unspecified</pose>
		<truncated>0</truncated>
		<difficult>0</difficult>
		<bndbox>
			<xmin>371</xmin>
			<ymin>1</ymin>
			<xmax>512</xmax>
			<ymax>336</ymax>
		</bndbox>
	</object>
	<object>
		<name>weak_entity</name>
		<pose>Unspecified</pose>
		<truncated>0</truncated>
		<difficult>0</difficult>
		<bndbox>
			<xmin>1</xmin>
			<ymin>20</ymin>
			<xmax>156</xmax>
			<ymax>141</ymax>
		</bndbox>
	</object>
	<object>
		<name>rel</name>
		<pose>Unspecified</pose>
		<truncated>0</truncated>
		<difficult>0</difficult>
		<bndbox>
			<xmin>206</xmin>
			<ymin>172</ymin>
			<xmax>300</xmax>
			<ymax>220</ymax>
		</bndbox>
	</object>
	<object>
		<name>ident_rel</name>
		<pose>Unspecified</pose>
		<truncated>0</truncated>
		<difficult>0</difficult>
		<bndbox>
			<xmin>200</xmin>
			<ymin>53</ymin>
			<xmax>311</xmax>
			<ymax>111</ymax>
		</bndbox>
	</object>
</annotation>